myeventhub/__init__.py
myeventhub/eventhub.py
myeventhub/interface.py
myeventhub-0.1.0.dist-info/METADATA
myeventhub-0.1.0.dist-info/WHEEL
myeventhub-0.1.0.dist-info/top_level.txt
myeventhub-0.1.0.dist-info/RECORD
