Metadata-Version: 2.1
Name: myeventhub
Version: 0.1.0
Summary: My first Python library
Author: Me
